fastq_utils/__init__.py
fastq_utils/tests.py
hubmap_fastq_utils-0.2.5.dist-info/LICENSE
hubmap_fastq_utils-0.2.5.dist-info/METADATA
hubmap_fastq_utils-0.2.5.dist-info/WHEEL
hubmap_fastq_utils-0.2.5.dist-info/top_level.txt
hubmap_fastq_utils-0.2.5.dist-info/RECORD
