Metadata-Version: 2.1
Name: hubmap-fastq-utils
Version: 0.2.5
Summary: FASTQ utility functions for HuBMAP computational pipelines
Home-page: https://github.com/hubmapconsortium/fastq-utils
Author: Matt Ruffalo
Author-email: mruffalo@cs.cmu.edu
License: GPLv3
Keywords: fastq
Classifier: Development Status :: 4 - Beta
Classifier: Intended Audience :: Developers
Classifier: Topic :: Software Development
Classifier: License :: OSI Approved :: MIT License
Classifier: Programming Language :: Python :: 3 :: Only
Classifier: Programming Language :: Python :: 3.6
Classifier: Programming Language :: Python :: 3.7
Classifier: Programming Language :: Python :: 3.8
Requires-Python: >=3.6
License-File: LICENSE
